plasma_comm/__init__.py
plasma_comm/__init__.pyi
plasma_comm/comm.py
plasma_comm/comm.pyi
plasma_comm/py.typed
plasma_comm/tests.py
plasma_comm/tests.pyi
plasma_comm-0.1.7.dist-info/WHEEL
plasma_comm-0.1.7.dist-info/METADATA
plasma_comm-0.1.7.dist-info/RECORD
