Metadata-Version: 2.1
Name: plasma-comm
Version: 0.1.7
Summary: Common code for plasma opensource packages.
Author: Damian Krystkiewicz
Author-email: damian.krystkiewicz@gmail.com
Requires-Python: >=3.6.1,<4.0
Classifier: Programming Language :: Python :: 3
Classifier: Programming Language :: Python :: 3.7
Classifier: Programming Language :: Python :: 3.8
